sc2_helper-0.2.1.dist-info/METADATA
sc2_helper-0.2.1.dist-info/WHEEL
sc2_helper/combat_simulator.py
sc2_helper/helper_functions.py
sc2_helper/test.py
sc2_helper/__init__.py
sc2_helper/sc2_helper.cp310-win_amd64.pyd
sc2_helper-0.2.1.dist-info/RECORD
