Metadata-Version: 2.1
Name: sc2_helper
Version: 0.2.1
